AUTHORS
LICENSE
MANIFEST.in
README.rst
setup.py
trunk/__init__.py
trunk/queue.py
trunk/transport.py
trunk/utils.py
trunk.egg-info/PKG-INFO
trunk.egg-info/SOURCES.txt
trunk.egg-info/dependency_links.txt
trunk.egg-info/not-zip-safe
trunk.egg-info/requires.txt
trunk.egg-info/top_level.txt