Metadata-Version: 1.1
Name: trunk
Version: 0.3.0
Summary: Making postgres listen/notify easier.
Home-page: https://github.com/cyberdelia/trunk
Author: Timothée Peignier
Author-email: timothee.peignier@tryphon.org
License: MIT
Platform: UNKNOWN
Classifier: Intended Audience :: Developers
Classifier: License :: OSI Approved :: MIT License
Classifier: Operating System :: OS Independent
Classifier: Programming Language :: Python
Classifier: Topic :: Utilities
